{"commit":{"id":"48ecd9d79b1b1c23ef04dfa67d6784cec6847f7c","url":"/arquillian/arquillian-extension-persistence/commit/48ecd9d79b1b1c23ef04dfa67d6784cec6847f7c","author":{"name":"Bartosz Majsak","email":"bartosz.majsak@gmail.com","login":"bartoszmajsak"},"authored_date":"2011-10-30T12:34:25-07:00","tree":"5f5c6bdadd823d7394f6c69dc7943d4fd4c13fe4","parents":[{"id":"8918ee25bc26e7ede9b4dde5c0459b04e7db0563"}],"message":"Turned off dumping database state during tests execution.","modified":[{"filename":"int-tests/src/test/resources-glassfish-3.1/arquillian.xml","diff":"@@ -10,18 +10,13 @@\n \n   <container qualifier=\"glassfish-embedded\" default=\"true\">\n     <configuration>\n-      <!-- \n-      <property name=\"configurationXml\">file:////home/bmajsak/dev/workspace/jboss/arquillian/arquillian-extension-persistence/impl/src/test/resources/glassfish-config.xml</property>\n-       -->\n       <property name=\"sunResourcesXml\">src/test/resources-glassfish-3.1/glassfish-resources.xml</property>\n       <property name=\"bindHttpPort\">9090</property>\n     </configuration>\n   </container>\n \n   <extension qualifier=\"persistence\">\n-    <property name=\"defaultDataSource\">arq/hsql</property>\n-    <property name=\"dumpData\">true</property>\n-    <property name=\"dumpDirectory\">/home/bmajsak/db-dumps</property>\n+    <property name=\"defaultDataSource\">arq/hsql</property>  \n     <property name=\"initStatement\">set referential_integrity FALSE</property>\n   </extension>\n "}],"committed_date":"2011-10-30T12:34:25-07:00","committer":{"name":"Bartosz Majsak","email":"bartosz.majsak@gmail.com","login":"bartoszmajsak"}}}